<annotation>
  <folder>/content/drive/MyDrive/images/AUG/images</folder>
  <filename>maksssksksss784_5.png</filename>
  <path>/content/drive/MyDrive/images/AUG/images/maksssksksss784_5.png</path>
  <source>
    <database>Unknown</database>
  </source>
  <size>
    <width>289</width>
    <height>172</height>
    <depth>3</depth>
  </size>
  <segmented>0</segmented>
  <object>
    <name>without_mask</name>
    <pose>Unspecified</pose>
    <truncated>0</truncated>
    <difficult>0</difficult>
    <bndbox>
      <xmin>24</xmin>
      <ymin>39</ymin>
      <xmax>40</xmax>
      <ymax>56</ymax>
    </bndbox>
  </object>
  <object>
    <name>with_mask</name>
    <pose>Unspecified</pose>
    <truncated>0</truncated>
    <difficult>0</difficult>
    <bndbox>
      <xmin>42</xmin>
      <ymin>40</ymin>
      <xmax>63</xmax>
      <ymax>64</ymax>
    </bndbox>
  </object>
  <object>
    <name>with_mask</name>
    <pose>Unspecified</pose>
    <truncated>0</truncated>
    <difficult>0</difficult>
    <bndbox>
      <xmin>75</xmin>
      <ymin>55</ymin>
      <xmax>96</xmax>
      <ymax>77</ymax>
    </bndbox>
  </object>
  <object>
    <name>with_mask</name>
    <pose>Unspecified</pose>
    <truncated>0</truncated>
    <difficult>0</difficult>
    <bndbox>
      <xmin>90</xmin>
      <ymin>31</ymin>
      <xmax>112</xmax>
      <ymax>56</ymax>
    </bndbox>
  </object>
  <object>
    <name>with_mask</name>
    <pose>Unspecified</pose>
    <truncated>0</truncated>
    <difficult>0</difficult>
    <bndbox>
      <xmin>108</xmin>
      <ymin>59</ymin>
      <xmax>131</xmax>
      <ymax>82</ymax>
    </bndbox>
  </object>
  <object>
    <name>with_mask</name>
    <pose>Unspecified</pose>
    <truncated>0</truncated>
    <difficult>0</difficult>
    <bndbox>
      <xmin>135</xmin>
      <ymin>42</ymin>
      <xmax>156</xmax>
      <ymax>66</ymax>
    </bndbox>
  </object>
  <object>
    <name>with_mask</name>
    <pose>Unspecified</pose>
    <truncated>0</truncated>
    <difficult>0</difficult>
    <bndbox>
      <xmin>178</xmin>
      <ymin>31</ymin>
      <xmax>201</xmax>
      <ymax>56</ymax>
    </bndbox>
  </object>
  <object>
    <name>with_mask</name>
    <pose>Unspecified</pose>
    <truncated>0</truncated>
    <difficult>0</difficult>
    <bndbox>
      <xmin>205</xmin>
      <ymin>54</ymin>
      <xmax>227</xmax>
      <ymax>77</ymax>
    </bndbox>
  </object>
  <object>
    <name>with_mask</name>
    <pose>Unspecified</pose>
    <truncated>0</truncated>
    <difficult>0</difficult>
    <bndbox>
      <xmin>234</xmin>
      <ymin>56</ymin>
      <xmax>253</xmax>
      <ymax>83</ymax>
    </bndbox>
  </object>
</annotation>
