<annotation>
  <folder>/content/drive/MyDrive/images/AUG/images</folder>
  <filename>maksssksksss414_9.png</filename>
  <path>/content/drive/MyDrive/images/AUG/images/maksssksksss414_9.png</path>
  <source>
    <database>Unknown</database>
  </source>
  <size>
    <width>313</width>
    <height>189</height>
    <depth>3</depth>
  </size>
  <segmented>0</segmented>
  <object>
    <name>with_mask</name>
    <pose>Unspecified</pose>
    <truncated>0</truncated>
    <difficult>0</difficult>
    <bndbox>
      <xmin>197</xmin>
      <ymin>73</ymin>
      <xmax>219</xmax>
      <ymax>101</ymax>
    </bndbox>
  </object>
  <object>
    <name>with_mask</name>
    <pose>Unspecified</pose>
    <truncated>0</truncated>
    <difficult>0</difficult>
    <bndbox>
      <xmin>217</xmin>
      <ymin>45</ymin>
      <xmax>233</xmax>
      <ymax>59</ymax>
    </bndbox>
  </object>
  <object>
    <name>with_mask</name>
    <pose>Unspecified</pose>
    <truncated>0</truncated>
    <difficult>0</difficult>
    <bndbox>
      <xmin>140</xmin>
      <ymin>26</ymin>
      <xmax>159</xmax>
      <ymax>45</ymax>
    </bndbox>
  </object>
  <object>
    <name>with_mask</name>
    <pose>Unspecified</pose>
    <truncated>0</truncated>
    <difficult>0</difficult>
    <bndbox>
      <xmin>53</xmin>
      <ymin>14</ymin>
      <xmax>75</xmax>
      <ymax>39</ymax>
    </bndbox>
  </object>
</annotation>
