<annotation>
  <folder>/content/drive/MyDrive/images/AUG/images</folder>
  <filename>maksssksksss137_1.png</filename>
  <path>/content/drive/MyDrive/images/AUG/images/maksssksksss137_1.png</path>
  <source>
    <database>Unknown</database>
  </source>
  <size>
    <width>400</width>
    <height>400</height>
    <depth>3</depth>
  </size>
  <segmented>0</segmented>
  <object>
    <name>without_mask</name>
    <pose>Unspecified</pose>
    <truncated>0</truncated>
    <difficult>0</difficult>
    <bndbox>
      <xmin>53</xmin>
      <ymin>257</ymin>
      <xmax>38</xmax>
      <ymax>239</ymax>
    </bndbox>
  </object>
  <object>
    <name>without_mask</name>
    <pose>Unspecified</pose>
    <truncated>0</truncated>
    <difficult>0</difficult>
    <bndbox>
      <xmin>95</xmin>
      <ymin>254</ymin>
      <xmax>76</xmax>
      <ymax>236</ymax>
    </bndbox>
  </object>
  <object>
    <name>with_mask</name>
    <pose>Unspecified</pose>
    <truncated>0</truncated>
    <difficult>0</difficult>
    <bndbox>
      <xmin>131</xmin>
      <ymin>258</ymin>
      <xmax>114</xmax>
      <ymax>237</ymax>
    </bndbox>
  </object>
  <object>
    <name>with_mask</name>
    <pose>Unspecified</pose>
    <truncated>0</truncated>
    <difficult>0</difficult>
    <bndbox>
      <xmin>175</xmin>
      <ymin>235</ymin>
      <xmax>158</xmax>
      <ymax>215</ymax>
    </bndbox>
  </object>
  <object>
    <name>without_mask</name>
    <pose>Unspecified</pose>
    <truncated>0</truncated>
    <difficult>0</difficult>
    <bndbox>
      <xmin>241</xmin>
      <ymin>247</ymin>
      <xmax>217</xmax>
      <ymax>226</ymax>
    </bndbox>
  </object>
  <object>
    <name>without_mask</name>
    <pose>Unspecified</pose>
    <truncated>0</truncated>
    <difficult>0</difficult>
    <bndbox>
      <xmin>310</xmin>
      <ymin>242</ymin>
      <xmax>283</xmax>
      <ymax>219</ymax>
    </bndbox>
  </object>
</annotation>
