<annotation>
  <folder>/content/drive/MyDrive/images/AUG/images</folder>
  <filename>maksssksksss427_4.png</filename>
  <path>/content/drive/MyDrive/images/AUG/images/maksssksksss427_4.png</path>
  <source>
    <database>Unknown</database>
  </source>
  <size>
    <width>313</width>
    <height>165</height>
    <depth>3</depth>
  </size>
  <segmented>0</segmented>
  <object>
    <name>with_mask</name>
    <pose>Unspecified</pose>
    <truncated>0</truncated>
    <difficult>0</difficult>
    <bndbox>
      <xmin>220</xmin>
      <ymin>63</ymin>
      <xmax>170</xmax>
      <ymax>117</ymax>
    </bndbox>
  </object>
  <object>
    <name>with_mask</name>
    <pose>Unspecified</pose>
    <truncated>0</truncated>
    <difficult>0</difficult>
    <bndbox>
      <xmin>273</xmin>
      <ymin>98</ymin>
      <xmax>259</xmax>
      <ymax>112</ymax>
    </bndbox>
  </object>
  <object>
    <name>with_mask</name>
    <pose>Unspecified</pose>
    <truncated>0</truncated>
    <difficult>0</difficult>
    <bndbox>
      <xmin>145</xmin>
      <ymin>97</ymin>
      <xmax>127</xmax>
      <ymax>115</ymax>
    </bndbox>
  </object>
  <object>
    <name>with_mask</name>
    <pose>Unspecified</pose>
    <truncated>0</truncated>
    <difficult>0</difficult>
    <bndbox>
      <xmin>80</xmin>
      <ymin>96</ymin>
      <xmax>5</xmax>
      <ymax>165</ymax>
    </bndbox>
  </object>
</annotation>
