<annotation>
  <folder>/content/drive/MyDrive/images/AUG/images</folder>
  <filename>maksssksksss789_6.png</filename>
  <path>/content/drive/MyDrive/images/AUG/images/maksssksksss789_6.png</path>
  <source>
    <database>Unknown</database>
  </source>
  <size>
    <width>312</width>
    <height>203</height>
    <depth>3</depth>
  </size>
  <segmented>0</segmented>
  <object>
    <name>with_mask</name>
    <pose>Unspecified</pose>
    <truncated>0</truncated>
    <difficult>0</difficult>
    <bndbox>
      <xmin>46</xmin>
      <ymin>180</ymin>
      <xmax>25</xmax>
      <ymax>155</ymax>
    </bndbox>
  </object>
  <object>
    <name>with_mask</name>
    <pose>Unspecified</pose>
    <truncated>0</truncated>
    <difficult>0</difficult>
    <bndbox>
      <xmin>139</xmin>
      <ymin>169</ymin>
      <xmax>124</xmax>
      <ymax>158</ymax>
    </bndbox>
  </object>
  <object>
    <name>with_mask</name>
    <pose>Unspecified</pose>
    <truncated>0</truncated>
    <difficult>0</difficult>
    <bndbox>
      <xmin>223</xmin>
      <ymin>161</ymin>
      <xmax>209</xmax>
      <ymax>147</ymax>
    </bndbox>
  </object>
  <object>
    <name>with_mask</name>
    <pose>Unspecified</pose>
    <truncated>0</truncated>
    <difficult>0</difficult>
    <bndbox>
      <xmin>235</xmin>
      <ymin>171</ymin>
      <xmax>223</xmax>
      <ymax>156</ymax>
    </bndbox>
  </object>
</annotation>
