<annotation>
  <folder>/content/drive/MyDrive/images/AUG/images</folder>
  <filename>maksssksksss383_8.png</filename>
  <path>/content/drive/MyDrive/images/AUG/images/maksssksksss383_8.png</path>
  <source>
    <database>Unknown</database>
  </source>
  <size>
    <width>255</width>
    <height>328</height>
    <depth>3</depth>
  </size>
  <segmented>0</segmented>
  <object>
    <name>with_mask</name>
    <pose>Unspecified</pose>
    <truncated>0</truncated>
    <difficult>0</difficult>
    <bndbox>
      <xmin>74</xmin>
      <ymin>108</ymin>
      <xmax>153</xmax>
      <ymax>208</ymax>
    </bndbox>
  </object>
</annotation>
