<annotation>
  <folder>/content/drive/MyDrive/images/AUG/images</folder>
  <filename>maksssksksss513_9.png</filename>
  <path>/content/drive/MyDrive/images/AUG/images/maksssksksss513_9.png</path>
  <source>
    <database>Unknown</database>
  </source>
  <size>
    <width>267</width>
    <height>400</height>
    <depth>3</depth>
  </size>
  <segmented>0</segmented>
  <object>
    <name>with_mask</name>
    <pose>Unspecified</pose>
    <truncated>0</truncated>
    <difficult>0</difficult>
    <bndbox>
      <xmin>70</xmin>
      <ymin>121</ymin>
      <xmax>101</xmax>
      <ymax>159</ymax>
    </bndbox>
  </object>
  <object>
    <name>with_mask</name>
    <pose>Unspecified</pose>
    <truncated>0</truncated>
    <difficult>0</difficult>
    <bndbox>
      <xmin>107</xmin>
      <ymin>115</ymin>
      <xmax>135</xmax>
      <ymax>144</ymax>
    </bndbox>
  </object>
  <object>
    <name>with_mask</name>
    <pose>Unspecified</pose>
    <truncated>0</truncated>
    <difficult>0</difficult>
    <bndbox>
      <xmin>179</xmin>
      <ymin>125</ymin>
      <xmax>208</xmax>
      <ymax>156</ymax>
    </bndbox>
  </object>
</annotation>
