<annotation>
  <folder>/content/drive/MyDrive/images/AUG/images</folder>
  <filename>maksssksksss511_5.png</filename>
  <path>/content/drive/MyDrive/images/AUG/images/maksssksksss511_5.png</path>
  <source>
    <database>Unknown</database>
  </source>
  <size>
    <width>302</width>
    <height>231</height>
    <depth>3</depth>
  </size>
  <segmented>0</segmented>
  <object>
    <name>with_mask</name>
    <pose>Unspecified</pose>
    <truncated>0</truncated>
    <difficult>0</difficult>
    <bndbox>
      <xmin>180</xmin>
      <ymin>150</ymin>
      <xmax>115</xmax>
      <ymax>90</ymax>
    </bndbox>
  </object>
</annotation>
