<annotation>
  <folder>/content/drive/MyDrive/images/AUG/images</folder>
  <filename>maksssksksss693_8.png</filename>
  <path>/content/drive/MyDrive/images/AUG/images/maksssksksss693_8.png</path>
  <source>
    <database>Unknown</database>
  </source>
  <size>
    <width>245</width>
    <height>335</height>
    <depth>3</depth>
  </size>
  <segmented>0</segmented>
  <object>
    <name>mask_weared_incorrect</name>
    <pose>Unspecified</pose>
    <truncated>0</truncated>
    <difficult>0</difficult>
    <bndbox>
      <xmin>108</xmin>
      <ymin>32</ymin>
      <xmax>131</xmax>
      <ymax>59</ymax>
    </bndbox>
  </object>
  <object>
    <name>with_mask</name>
    <pose>Unspecified</pose>
    <truncated>0</truncated>
    <difficult>0</difficult>
    <bndbox>
      <xmin>55</xmin>
      <ymin>29</ymin>
      <xmax>83</xmax>
      <ymax>56</ymax>
    </bndbox>
  </object>
</annotation>
