<annotation>
  <folder>/content/drive/MyDrive/images/AUG/images</folder>
  <filename>maksssksksss409_9.png</filename>
  <path>/content/drive/MyDrive/images/AUG/images/maksssksksss409_9.png</path>
  <source>
    <database>Unknown</database>
  </source>
  <size>
    <width>226</width>
    <height>295</height>
    <depth>3</depth>
  </size>
  <segmented>0</segmented>
  <object>
    <name>with_mask</name>
    <pose>Unspecified</pose>
    <truncated>0</truncated>
    <difficult>0</difficult>
    <bndbox>
      <xmin>68</xmin>
      <ymin>152</ymin>
      <xmax>127</xmax>
      <ymax>233</ymax>
    </bndbox>
  </object>
</annotation>
