<annotation>
  <folder>/content/drive/MyDrive/images/AUG/images</folder>
  <filename>maksssksksss507_7.png</filename>
  <path>/content/drive/MyDrive/images/AUG/images/maksssksksss507_7.png</path>
  <source>
    <database>Unknown</database>
  </source>
  <size>
    <width>284</width>
    <height>146</height>
    <depth>3</depth>
  </size>
  <segmented>0</segmented>
  <object>
    <name>with_mask</name>
    <pose>Unspecified</pose>
    <truncated>0</truncated>
    <difficult>0</difficult>
    <bndbox>
      <xmin>165</xmin>
      <ymin>26</ymin>
      <xmax>80</xmax>
      <ymax>111</ymax>
    </bndbox>
  </object>
</annotation>
