<annotation>
  <folder>/content/drive/MyDrive/images/AUG/images</folder>
  <filename>maksssksksss510_2.png</filename>
  <path>/content/drive/MyDrive/images/AUG/images/maksssksksss510_2.png</path>
  <source>
    <database>Unknown</database>
  </source>
  <size>
    <width>319</width>
    <height>224</height>
    <depth>3</depth>
  </size>
  <segmented>0</segmented>
  <object>
    <name>with_mask</name>
    <pose>Unspecified</pose>
    <truncated>0</truncated>
    <difficult>0</difficult>
    <bndbox>
      <xmin>37</xmin>
      <ymin>44</ymin>
      <xmax>89</xmax>
      <ymax>97</ymax>
    </bndbox>
  </object>
  <object>
    <name>with_mask</name>
    <pose>Unspecified</pose>
    <truncated>0</truncated>
    <difficult>0</difficult>
    <bndbox>
      <xmin>144</xmin>
      <ymin>79</ymin>
      <xmax>164</xmax>
      <ymax>99</ymax>
    </bndbox>
  </object>
  <object>
    <name>with_mask</name>
    <pose>Unspecified</pose>
    <truncated>0</truncated>
    <difficult>0</difficult>
    <bndbox>
      <xmin>195</xmin>
      <ymin>78</ymin>
      <xmax>218</xmax>
      <ymax>108</ymax>
    </bndbox>
  </object>
  <object>
    <name>with_mask</name>
    <pose>Unspecified</pose>
    <truncated>0</truncated>
    <difficult>0</difficult>
    <bndbox>
      <xmin>239</xmin>
      <ymin>76</ymin>
      <xmax>271</xmax>
      <ymax>102</ymax>
    </bndbox>
  </object>
</annotation>
