<annotation>
  <folder>/content/drive/MyDrive/images/AUG/images</folder>
  <filename>maksssksksss250_6.png</filename>
  <path>/content/drive/MyDrive/images/AUG/images/maksssksksss250_6.png</path>
  <source>
    <database>Unknown</database>
  </source>
  <size>
    <width>400</width>
    <height>267</height>
    <depth>3</depth>
  </size>
  <segmented>0</segmented>
  <object>
    <name>with_mask</name>
    <pose>Unspecified</pose>
    <truncated>0</truncated>
    <difficult>0</difficult>
    <bndbox>
      <xmin>220</xmin>
      <ymin>160</ymin>
      <xmax>178</xmax>
      <ymax>203</ymax>
    </bndbox>
  </object>
  <object>
    <name>without_mask</name>
    <pose>Unspecified</pose>
    <truncated>0</truncated>
    <difficult>0</difficult>
    <bndbox>
      <xmin>315</xmin>
      <ymin>164</ymin>
      <xmax>282</xmax>
      <ymax>202</ymax>
    </bndbox>
  </object>
  <object>
    <name>without_mask</name>
    <pose>Unspecified</pose>
    <truncated>0</truncated>
    <difficult>0</difficult>
    <bndbox>
      <xmin>265</xmin>
      <ymin>203</ymin>
      <xmax>246</xmax>
      <ymax>231</ymax>
    </bndbox>
  </object>
  <object>
    <name>mask_weared_incorrect</name>
    <pose>Unspecified</pose>
    <truncated>0</truncated>
    <difficult>0</difficult>
    <bndbox>
      <xmin>374</xmin>
      <ymin>182</ymin>
      <xmax>341</xmax>
      <ymax>225</ymax>
    </bndbox>
  </object>
  <object>
    <name>mask_weared_incorrect</name>
    <pose>Unspecified</pose>
    <truncated>0</truncated>
    <difficult>0</difficult>
    <bndbox>
      <xmin>59</xmin>
      <ymin>182</ymin>
      <xmax>15</xmax>
      <ymax>235</ymax>
    </bndbox>
  </object>
</annotation>
