<annotation>
  <folder>/content/drive/MyDrive/images/AUG/images</folder>
  <filename>maksssksksss756_5.png</filename>
  <path>/content/drive/MyDrive/images/AUG/images/maksssksksss756_5.png</path>
  <source>
    <database>Unknown</database>
  </source>
  <size>
    <width>400</width>
    <height>267</height>
    <depth>3</depth>
  </size>
  <segmented>0</segmented>
  <object>
    <name>with_mask</name>
    <pose>Unspecified</pose>
    <truncated>0</truncated>
    <difficult>0</difficult>
    <bndbox>
      <xmin>213</xmin>
      <ymin>175</ymin>
      <xmax>178</xmax>
      <ymax>217</ymax>
    </bndbox>
  </object>
  <object>
    <name>mask_weared_incorrect</name>
    <pose>Unspecified</pose>
    <truncated>0</truncated>
    <difficult>0</difficult>
    <bndbox>
      <xmin>315</xmin>
      <ymin>166</ymin>
      <xmax>278</xmax>
      <ymax>203</ymax>
    </bndbox>
  </object>
</annotation>
