<annotation>
  <folder>/content/drive/MyDrive/images/AUG/images</folder>
  <filename>maksssksksss540_10.png</filename>
  <path>/content/drive/MyDrive/images/AUG/images/maksssksksss540_10.png</path>
  <source>
    <database>Unknown</database>
  </source>
  <size>
    <width>241</width>
    <height>309</height>
    <depth>3</depth>
  </size>
  <segmented>0</segmented>
  <object>
    <name>without_mask</name>
    <pose>Unspecified</pose>
    <truncated>0</truncated>
    <difficult>0</difficult>
    <bndbox>
      <xmin>85</xmin>
      <ymin>106</ymin>
      <xmax>156</xmax>
      <ymax>192</ymax>
    </bndbox>
  </object>
</annotation>
